<?xml version="1.0" encoding="UTF-8"?>
<record_update table="wf_workflow_version">
    <wf_workflow_version action="INSERT_OR_UPDATE">
        <active>true</active>
        <activity_stages>{"activities":{},"subflows":[],"stages":{},"ends":["d744b3204f31030031243ce18110c7cd"]}</activity_stages>
        <after_business_rules>false</after_business_rules>
        <checked_out/>
        <checked_out_by/>
        <column_renderer display_value="Workflow-driven">a56213111b030100adca1e094f0713ac</column_renderer>
        <condition/>
        <condition_type>run_match</condition_type>
        <description>testing</description>
        <expected_sequences>d344b3204f31030031243ce18110c7cd,ff64f7604f31030031243ce18110c74f,04b47b604f31030031243ce18110c782,d744b3204f31030031243ce18110c7cd</expected_sequences>
        <expected_time>1970-01-01 14:00:00</expected_time>
        <expected_time_type/>
        <full_sequences>d344b3204f31030031243ce18110c7cd,ff64f7604f31030031243ce18110c74f,04b47b604f31030031243ce18110c782,d744b3204f31030031243ce18110c7cd</full_sequences>
        <journal/>
        <max_activity_count>100</max_activity_count>
        <name>Myworkflow</name>
        <not_cacheable>false</not_cacheable>
        <on_cancel><![CDATA[// This script executes if the workflow is cancelled.// The global variable context_sys_id contains the sys_id of the cancelled workflow context.]]></on_cancel>
        <order>100</order>
        <pin_type>set_by_activity</pin_type>
        <published>true</published>
        <relative_duration/>
        <requires_ert>true</requires_ert>
        <run_multiple>false</run_multiple>
        <schedule/>
        <stage_field/>
        <stage_order>computed</stage_order>
        <start display_value="Begin">d344b3204f31030031243ce18110c7cd</start>
        <sys_created_by>admin</sys_created_by>
        <sys_created_on>2017-10-11 09:08:03</sys_created_on>
        <sys_id>c2b377604f31030031243ce18110c7e5</sys_id>
        <sys_mod_count>6</sys_mod_count>
        <sys_updated_by>admin</sys_updated_by>
        <sys_updated_on>2017-10-11 09:12:44</sys_updated_on>
        <table>sc_task</table>
        <timezone/>
        <validated>false</validated>
        <workflow display_value="Myworkflow">1344b3204f31030031243ce18110c7cd</workflow>
    </wf_workflow_version>
    <wf_workflow action="INSERT_OR_UPDATE">
        <access>public</access>
        <description>testing</description>
        <name>Myworkflow</name>
        <preview/>
        <sys_class_name>wf_workflow</sys_class_name>
        <sys_created_by>admin</sys_created_by>
        <sys_created_on>2017-10-11 09:08:04</sys_created_on>
        <sys_customer_update>true</sys_customer_update>
        <sys_domain>global</sys_domain>
        <sys_domain_path>/</sys_domain_path>
        <sys_id>1344b3204f31030031243ce18110c7cd</sys_id>
        <sys_mod_count>0</sys_mod_count>
        <sys_name>Myworkflow</sys_name>
        <sys_overrides/>
        <sys_package display_value="Ravikiran" source="x_9544_ravikiran">c3512d034f20030031243ce18110c75f</sys_package>
        <sys_policy/>
        <sys_replace_on_upgrade>false</sys_replace_on_upgrade>
        <sys_scope display_value="Ravikiran">c3512d034f20030031243ce18110c75f</sys_scope>
        <sys_update_name>wf_workflow_1344b3204f31030031243ce18110c7cd</sys_update_name>
        <sys_updated_by>admin</sys_updated_by>
        <sys_updated_on>2017-10-11 09:08:04</sys_updated_on>
        <table>sc_task</table>
        <template>false</template>
        <vars/>
    </wf_workflow>
    <wf_activity action="INSERT_OR_UPDATE">
        <activity_definition display_value="Begin">c7a5e32c0a0a0b3a002377c24ed8ea76</activity_definition>
        <activity_definition_updated>false</activity_definition_updated>
        <databus_lookup_id>1</databus_lookup_id>
        <height/>
        <input/>
        <is_parent>false</is_parent>
        <name>Begin</name>
        <new_activity_definition/>
        <notes/>
        <out_of_date>false</out_of_date>
        <parent/>
        <pinned>false</pinned>
        <pinned_version/>
        <stage/>
        <sys_created_by>admin</sys_created_by>
        <sys_created_on>2017-10-11 09:08:04</sys_created_on>
        <sys_id>d344b3204f31030031243ce18110c7cd</sys_id>
        <sys_mod_count>0</sys_mod_count>
        <sys_updated_by>admin</sys_updated_by>
        <sys_updated_on>2017-10-11 09:08:04</sys_updated_on>
        <timeout>1970-01-01 00:00:00</timeout>
        <vars/>
        <width>80</width>
        <workflow_version display_value="Myworkflow">c2b377604f31030031243ce18110c7e5</workflow_version>
        <x>20</x>
        <y>20</y>
    </wf_activity>
    <sys_variable_value action="delete_multiple" query="document_key=d344b3204f31030031243ce18110c7cd"/>
    <wf_condition action="INSERT_OR_UPDATE">
        <activity display_value="Begin">d344b3204f31030031243ce18110c7cd</activity>
        <condition>true</condition>
        <condition_default/>
        <condition_type>standard</condition_type>
        <else_flag>false</else_flag>
        <error>false</error>
        <event>false</event>
        <event_name/>
        <is_positive>true</is_positive>
        <name>Always</name>
        <order>0</order>
        <short_description/>
        <skip_during_generate>false</skip_during_generate>
        <sys_created_by>admin</sys_created_by>
        <sys_created_on>2017-10-11 09:08:04</sys_created_on>
        <sys_id>5744b3204f31030031243ce18110c7cd</sys_id>
        <sys_mod_count>0</sys_mod_count>
        <sys_updated_by>admin</sys_updated_by>
        <sys_updated_on>2017-10-11 09:08:04</sys_updated_on>
    </wf_condition>
    <wf_activity action="INSERT_OR_UPDATE">
        <activity_definition display_value="Run Script">db8c65aec0a8016501d00259bc7203a4</activity_definition>
        <activity_definition_updated>false</activity_definition_updated>
        <databus_lookup_id>3</databus_lookup_id>
        <height/>
        <input>{}</input>
        <is_parent>false</is_parent>
        <name>Capture the follow-up date</name>
        <new_activity_definition/>
        <notes/>
        <out_of_date>false</out_of_date>
        <parent/>
        <pinned>false</pinned>
        <pinned_version/>
        <stage/>
        <sys_created_by>admin</sys_created_by>
        <sys_created_on>2017-10-11 09:09:06</sys_created_on>
        <sys_id>ff64f7604f31030031243ce18110c74f</sys_id>
        <sys_mod_count>3</sys_mod_count>
        <sys_updated_by>admin</sys_updated_by>
        <sys_updated_on>2017-10-11 09:09:23</sys_updated_on>
        <timeout>1970-01-01 00:00:00</timeout>
        <vars/>
        <width/>
        <workflow_version display_value="Myworkflow">c2b377604f31030031243ce18110c7e5</workflow_version>
        <x>236</x>
        <y>34</y>
    </wf_activity>
    <sys_variable_value action="delete_multiple" query="document_key=ff64f7604f31030031243ce18110c74f"/>
    <sys_variable_value action="INSERT_OR_UPDATE">
        <document>wf_activity</document>
        <document_key>ff64f7604f31030031243ce18110c74f</document_key>
        <order>1</order>
        <sys_class_name>sys_variable_value</sys_class_name>
        <sys_created_by>admin</sys_created_by>
        <sys_created_on>2017-10-11 09:09:06</sys_created_on>
        <sys_id>ea84f7204f31030031243ce18110c72c</sys_id>
        <sys_mod_count>0</sys_mod_count>
        <sys_updated_by>admin</sys_updated_by>
        <sys_updated_on>2017-10-11 09:09:06</sys_updated_on>
        <value>workflow.scratchpad.followup1 = current.follow_up;</value>
        <variable display_value="">c35ddef20a0a0ba96248a7090eccd518</variable>
    </sys_variable_value>
    <sys_variable_value action="INSERT_OR_UPDATE">
        <document>wf_activity</document>
        <document_key>ff64f7604f31030031243ce18110c74f</document_key>
        <order>1</order>
        <sys_class_name>sys_variable_value</sys_class_name>
        <sys_created_by>admin</sys_created_by>
        <sys_created_on>2017-10-11 09:09:06</sys_created_on>
        <sys_id>ea84f7204f31030031243ce18110c72c</sys_id>
        <sys_mod_count>0</sys_mod_count>
        <sys_updated_by>admin</sys_updated_by>
        <sys_updated_on>2017-10-11 09:09:06</sys_updated_on>
        <value>workflow.scratchpad.followup1 = current.follow_up;</value>
        <variable display_value="">c35ddef20a0a0ba96248a7090eccd518</variable>
    </sys_variable_value>
    <wf_condition action="INSERT_OR_UPDATE">
        <activity display_value="Capture the follow-up date">ff64f7604f31030031243ce18110c74f</activity>
        <condition>true</condition>
        <condition_default/>
        <condition_type>standard</condition_type>
        <else_flag>false</else_flag>
        <error>false</error>
        <event>false</event>
        <event_name/>
        <is_positive>true</is_positive>
        <name>Always</name>
        <order>0</order>
        <short_description/>
        <skip_during_generate>false</skip_during_generate>
        <sys_created_by>admin</sys_created_by>
        <sys_created_on>2017-10-11 09:09:06</sys_created_on>
        <sys_id>6284f7204f31030031243ce18110c72d</sys_id>
        <sys_mod_count>0</sys_mod_count>
        <sys_updated_by>admin</sys_updated_by>
        <sys_updated_on>2017-10-11 09:09:06</sys_updated_on>
    </wf_condition>
    <wf_activity action="INSERT_OR_UPDATE">
        <activity_definition display_value="End">c7a66f7d0a0a0b3a004544a6d2f14076</activity_definition>
        <activity_definition_updated>false</activity_definition_updated>
        <databus_lookup_id>2</databus_lookup_id>
        <height/>
        <input/>
        <is_parent>false</is_parent>
        <name>End</name>
        <new_activity_definition/>
        <notes/>
        <out_of_date>false</out_of_date>
        <parent/>
        <pinned>false</pinned>
        <pinned_version/>
        <stage/>
        <sys_created_by>admin</sys_created_by>
        <sys_created_on>2017-10-11 09:08:04</sys_created_on>
        <sys_id>d744b3204f31030031243ce18110c7cd</sys_id>
        <sys_mod_count>1</sys_mod_count>
        <sys_updated_by>admin</sys_updated_by>
        <sys_updated_on>2017-10-11 09:08:11</sys_updated_on>
        <timeout>1970-01-01 00:00:00</timeout>
        <vars/>
        <width>80</width>
        <workflow_version display_value="Myworkflow">c2b377604f31030031243ce18110c7e5</workflow_version>
        <x>543</x>
        <y>296</y>
    </wf_activity>
    <sys_variable_value action="delete_multiple" query="document_key=d744b3204f31030031243ce18110c7cd"/>
    <wf_activity action="INSERT_OR_UPDATE">
        <activity_definition display_value="Timer">3961a1da0a0a0b5c00ecd84822f70d85</activity_definition>
        <activity_definition_updated>false</activity_definition_updated>
        <databus_lookup_id>4</databus_lookup_id>
        <height/>
        <input>{}</input>
        <is_parent>false</is_parent>
        <name>Wait for Follow-up to end</name>
        <new_activity_definition/>
        <notes/>
        <out_of_date>false</out_of_date>
        <parent/>
        <pinned>false</pinned>
        <pinned_version/>
        <stage/>
        <sys_created_by>admin</sys_created_by>
        <sys_created_on>2017-10-11 09:10:34</sys_created_on>
        <sys_id>04b47b604f31030031243ce18110c782</sys_id>
        <sys_mod_count>1</sys_mod_count>
        <sys_updated_by>admin</sys_updated_by>
        <sys_updated_on>2017-10-11 09:10:36</sys_updated_on>
        <timeout>1970-01-01 00:00:00</timeout>
        <vars/>
        <width/>
        <workflow_version display_value="Myworkflow">c2b377604f31030031243ce18110c7e5</workflow_version>
        <x>452</x>
        <y>118</y>
    </wf_activity>
    <sys_variable_value action="delete_multiple" query="document_key=04b47b604f31030031243ce18110c782"/>
    <sys_variable_value action="INSERT_OR_UPDATE">
        <document>wf_activity</document>
        <document_key>04b47b604f31030031243ce18110c782</document_key>
        <order>350</order>
        <sys_class_name>sys_variable_value</sys_class_name>
        <sys_created_by>admin</sys_created_by>
        <sys_created_on>2017-10-11 09:10:34</sys_created_on>
        <sys_id>00e4f7204f31030031243ce18110c7ff</sys_id>
        <sys_mod_count>0</sys_mod_count>
        <sys_updated_by>admin</sys_updated_by>
        <sys_updated_on>2017-10-11 09:10:34</sys_updated_on>
        <value/>
        <variable display_value="">4cbfe48a0a0a0b5200cf8b82cc6685f1</variable>
    </sys_variable_value>
    <sys_variable_value action="INSERT_OR_UPDATE">
        <document>wf_activity</document>
        <document_key>04b47b604f31030031243ce18110c782</document_key>
        <order>1320</order>
        <sys_class_name>sys_variable_value</sys_class_name>
        <sys_created_by>admin</sys_created_by>
        <sys_created_on>2017-10-11 09:10:34</sys_created_on>
        <sys_id>08e43b204f31030031243ce18110c700</sys_id>
        <sys_mod_count>0</sys_mod_count>
        <sys_updated_by>admin</sys_updated_by>
        <sys_updated_on>2017-10-11 09:10:34</sys_updated_on>
        <value/>
        <variable display_value="">4cc6788c0a0a0b5200e6743c94001b16</variable>
    </sys_variable_value>
    <sys_variable_value action="INSERT_OR_UPDATE">
        <document>wf_activity</document>
        <document_key>04b47b604f31030031243ce18110c782</document_key>
        <order>1310</order>
        <sys_class_name>sys_variable_value</sys_class_name>
        <sys_created_by>admin</sys_created_by>
        <sys_created_on>2017-10-11 09:10:34</sys_created_on>
        <sys_id>0ce4f7204f31030031243ce18110c7ff</sys_id>
        <sys_mod_count>0</sys_mod_count>
        <sys_updated_by>admin</sys_updated_by>
        <sys_updated_on>2017-10-11 09:10:34</sys_updated_on>
        <value>follow_up</value>
        <variable display_value="">21fd462c0a0a0b211c997276d7806c03</variable>
    </sys_variable_value>
    <sys_variable_value action="INSERT_OR_UPDATE">
        <document>wf_activity</document>
        <document_key>04b47b604f31030031243ce18110c782</document_key>
        <order>1350</order>
        <sys_class_name>sys_variable_value</sys_class_name>
        <sys_created_by>admin</sys_created_by>
        <sys_created_on>2017-10-11 09:10:34</sys_created_on>
        <sys_id>40e43b204f31030031243ce18110c701</sys_id>
        <sys_mod_count>0</sys_mod_count>
        <sys_updated_by>admin</sys_updated_by>
        <sys_updated_on>2017-10-11 09:10:34</sys_updated_on>
        <value/>
        <variable display_value="">4cc740fe0a0a0b520025dcf8e2ff78e7</variable>
    </sys_variable_value>
    <sys_variable_value action="INSERT_OR_UPDATE">
        <document>wf_activity</document>
        <document_key>04b47b604f31030031243ce18110c782</document_key>
        <order>1320</order>
        <sys_class_name>sys_variable_value</sys_class_name>
        <sys_created_by>admin</sys_created_by>
        <sys_created_on>2017-10-11 09:10:34</sys_created_on>
        <sys_id>44e43b204f31030031243ce18110c700</sys_id>
        <sys_mod_count>0</sys_mod_count>
        <sys_updated_by>admin</sys_updated_by>
        <sys_updated_on>2017-10-11 09:10:34</sys_updated_on>
        <value>08fcd0830a0a0b2600079f56b1adb9ae</value>
        <variable display_value="">4cc4a4030a0a0b52007334f001376dc5</variable>
    </sys_variable_value>
    <sys_variable_value action="INSERT_OR_UPDATE">
        <document>wf_activity</document>
        <document_key>04b47b604f31030031243ce18110c782</document_key>
        <order>1310</order>
        <sys_class_name>sys_variable_value</sys_class_name>
        <sys_created_by>admin</sys_created_by>
        <sys_created_on>2017-10-11 09:10:34</sys_created_on>
        <sys_id>48e4f7204f31030031243ce18110c7ff</sys_id>
        <sys_mod_count>0</sys_mod_count>
        <sys_updated_by>admin</sys_updated_by>
        <sys_updated_on>2017-10-11 09:10:34</sys_updated_on>
        <value>3bf802c20a0a0b52008e2859cd8abcf2</value>
        <variable display_value="">220cd53d0a0a0b214103bdc2ec5c7ab4</variable>
    </sys_variable_value>
    <sys_variable_value action="INSERT_OR_UPDATE">
        <document>wf_activity</document>
        <document_key>04b47b604f31030031243ce18110c782</document_key>
        <order>1350</order>
        <sys_class_name>sys_variable_value</sys_class_name>
        <sys_created_by>admin</sys_created_by>
        <sys_created_on>2017-10-11 09:10:34</sys_created_on>
        <sys_id>4ce4f7204f31030031243ce18110c7fe</sys_id>
        <sys_mod_count>0</sys_mod_count>
        <sys_updated_by>admin</sys_updated_by>
        <sys_updated_on>2017-10-11 09:10:34</sys_updated_on>
        <value/>
        <variable display_value="">4cc836da0a0a0b520083ebc07da2f47c</variable>
    </sys_variable_value>
    <sys_variable_value action="INSERT_OR_UPDATE">
        <document>wf_activity</document>
        <document_key>04b47b604f31030031243ce18110c782</document_key>
        <order>1360</order>
        <sys_class_name>sys_variable_value</sys_class_name>
        <sys_created_by>admin</sys_created_by>
        <sys_created_on>2017-10-11 09:10:34</sys_created_on>
        <sys_id>80e43b204f31030031243ce18110c700</sys_id>
        <sys_mod_count>0</sys_mod_count>
        <sys_updated_by>admin</sys_updated_by>
        <sys_updated_on>2017-10-11 09:10:34</sys_updated_on>
        <value/>
        <variable display_value="">292b2f0e0a0a0b215aa2dd2cbc578dc5</variable>
    </sys_variable_value>
    <sys_variable_value action="INSERT_OR_UPDATE">
        <document>wf_activity</document>
        <document_key>04b47b604f31030031243ce18110c782</document_key>
        <order>1310</order>
        <sys_class_name>sys_variable_value</sys_class_name>
        <sys_created_by>admin</sys_created_by>
        <sys_created_on>2017-10-11 09:10:34</sys_created_on>
        <sys_id>84e4f7204f31030031243ce18110c7ff</sys_id>
        <sys_mod_count>0</sys_mod_count>
        <sys_updated_by>admin</sys_updated_by>
        <sys_updated_on>2017-10-11 09:10:34</sys_updated_on>
        <value/>
        <variable display_value="">c35dc0df0a0a0ba96248a7098d737925</variable>
    </sys_variable_value>
    <sys_variable_value action="INSERT_OR_UPDATE">
        <document>wf_activity</document>
        <document_key>04b47b604f31030031243ce18110c782</document_key>
        <order>500</order>
        <sys_class_name>sys_variable_value</sys_class_name>
        <sys_created_by>admin</sys_created_by>
        <sys_created_on>2017-10-11 09:10:34</sys_created_on>
        <sys_id>88e4f7204f31030031243ce18110c7fe</sys_id>
        <sys_mod_count>0</sys_mod_count>
        <sys_updated_by>admin</sys_updated_by>
        <sys_updated_on>2017-10-11 09:10:34</sys_updated_on>
        <value/>
        <variable display_value="">220dc5a40a0a0b2109fbd28b8c4b6213</variable>
    </sys_variable_value>
    <sys_variable_value action="INSERT_OR_UPDATE">
        <document>wf_activity</document>
        <document_key>04b47b604f31030031243ce18110c782</document_key>
        <order>310</order>
        <sys_class_name>sys_variable_value</sys_class_name>
        <sys_created_by>admin</sys_created_by>
        <sys_created_on>2017-10-11 09:10:34</sys_created_on>
        <sys_id>8ce43b204f31030031243ce18110c700</sys_id>
        <sys_mod_count>0</sys_mod_count>
        <sys_updated_by>admin</sys_updated_by>
        <sys_updated_on>2017-10-11 09:10:34</sys_updated_on>
        <value>field</value>
        <variable display_value="">21f80cd00a0a0b2101fcd5b5defc0810</variable>
    </sys_variable_value>
    <sys_variable_value action="INSERT_OR_UPDATE">
        <document>wf_activity</document>
        <document_key>04b47b604f31030031243ce18110c782</document_key>
        <order>3000</order>
        <sys_class_name>sys_variable_value</sys_class_name>
        <sys_created_by>admin</sys_created_by>
        <sys_created_on>2017-10-11 09:10:34</sys_created_on>
        <sys_id>c0e4f7204f31030031243ce18110c7ff</sys_id>
        <sys_mod_count>0</sys_mod_count>
        <sys_updated_by>admin</sys_updated_by>
        <sys_updated_on>2017-10-11 09:10:34</sys_updated_on>
        <value>// Set 'answer' to the number of seconds this timer should wait&#13;
answer = 0;</value>
        <variable display_value="">293493710a0a0b2115e3e5b4fce1d12a</variable>
    </sys_variable_value>
    <sys_variable_value action="INSERT_OR_UPDATE">
        <document>wf_activity</document>
        <document_key>04b47b604f31030031243ce18110c782</document_key>
        <order>320</order>
        <sys_class_name>sys_variable_value</sys_class_name>
        <sys_created_by>admin</sys_created_by>
        <sys_created_on>2017-10-11 09:10:34</sys_created_on>
        <sys_id>c4e4f7204f31030031243ce18110c7fe</sys_id>
        <sys_mod_count>0</sys_mod_count>
        <sys_updated_by>admin</sys_updated_by>
        <sys_updated_on>2017-10-11 09:10:34</sys_updated_on>
        <value/>
        <variable display_value="">4cba34da0a0a0b5200798c86eafe1203</variable>
    </sys_variable_value>
    <sys_variable_value action="INSERT_OR_UPDATE">
        <document>wf_activity</document>
        <document_key>04b47b604f31030031243ce18110c782</document_key>
        <order>1360</order>
        <sys_class_name>sys_variable_value</sys_class_name>
        <sys_created_by>admin</sys_created_by>
        <sys_created_on>2017-10-11 09:10:34</sys_created_on>
        <sys_id>c8e43b204f31030031243ce18110c700</sys_id>
        <sys_mod_count>0</sys_mod_count>
        <sys_updated_by>admin</sys_updated_by>
        <sys_updated_on>2017-10-11 09:10:34</sys_updated_on>
        <value/>
        <variable display_value="">292c91070a0a0b212543d91ffde5014c</variable>
    </sys_variable_value>
    <sys_variable_value action="INSERT_OR_UPDATE">
        <document>wf_activity</document>
        <document_key>04b47b604f31030031243ce18110c782</document_key>
        <order>1360</order>
        <sys_class_name>sys_variable_value</sys_class_name>
        <sys_created_by>admin</sys_created_by>
        <sys_created_on>2017-10-11 09:10:34</sys_created_on>
        <sys_id>cce4f7204f31030031243ce18110c7ff</sys_id>
        <sys_mod_count>0</sys_mod_count>
        <sys_updated_by>admin</sys_updated_by>
        <sys_updated_on>2017-10-11 09:10:34</sys_updated_on>
        <value/>
        <variable display_value="">292bd15e0a0a0b215a040c701033e3c5</variable>
    </sys_variable_value>
    <sys_variable_value action="INSERT_OR_UPDATE">
        <document>wf_activity</document>
        <document_key>04b47b604f31030031243ce18110c782</document_key>
        <order>310</order>
        <sys_class_name>sys_variable_value</sys_class_name>
        <sys_created_by>admin</sys_created_by>
        <sys_created_on>2017-10-11 09:10:34</sys_created_on>
        <sys_id>8ce43b204f31030031243ce18110c700</sys_id>
        <sys_mod_count>0</sys_mod_count>
        <sys_updated_by>admin</sys_updated_by>
        <sys_updated_on>2017-10-11 09:10:34</sys_updated_on>
        <value>field</value>
        <variable display_value="">21f80cd00a0a0b2101fcd5b5defc0810</variable>
    </sys_variable_value>
    <sys_variable_value action="INSERT_OR_UPDATE">
        <document>wf_activity</document>
        <document_key>04b47b604f31030031243ce18110c782</document_key>
        <order>320</order>
        <sys_class_name>sys_variable_value</sys_class_name>
        <sys_created_by>admin</sys_created_by>
        <sys_created_on>2017-10-11 09:10:34</sys_created_on>
        <sys_id>c4e4f7204f31030031243ce18110c7fe</sys_id>
        <sys_mod_count>0</sys_mod_count>
        <sys_updated_by>admin</sys_updated_by>
        <sys_updated_on>2017-10-11 09:10:34</sys_updated_on>
        <value/>
        <variable display_value="">4cba34da0a0a0b5200798c86eafe1203</variable>
    </sys_variable_value>
    <sys_variable_value action="INSERT_OR_UPDATE">
        <document>wf_activity</document>
        <document_key>04b47b604f31030031243ce18110c782</document_key>
        <order>350</order>
        <sys_class_name>sys_variable_value</sys_class_name>
        <sys_created_by>admin</sys_created_by>
        <sys_created_on>2017-10-11 09:10:34</sys_created_on>
        <sys_id>00e4f7204f31030031243ce18110c7ff</sys_id>
        <sys_mod_count>0</sys_mod_count>
        <sys_updated_by>admin</sys_updated_by>
        <sys_updated_on>2017-10-11 09:10:34</sys_updated_on>
        <value/>
        <variable display_value="">4cbfe48a0a0a0b5200cf8b82cc6685f1</variable>
    </sys_variable_value>
    <sys_variable_value action="INSERT_OR_UPDATE">
        <document>wf_activity</document>
        <document_key>04b47b604f31030031243ce18110c782</document_key>
        <order>500</order>
        <sys_class_name>sys_variable_value</sys_class_name>
        <sys_created_by>admin</sys_created_by>
        <sys_created_on>2017-10-11 09:10:34</sys_created_on>
        <sys_id>88e4f7204f31030031243ce18110c7fe</sys_id>
        <sys_mod_count>0</sys_mod_count>
        <sys_updated_by>admin</sys_updated_by>
        <sys_updated_on>2017-10-11 09:10:34</sys_updated_on>
        <value/>
        <variable display_value="">220dc5a40a0a0b2109fbd28b8c4b6213</variable>
    </sys_variable_value>
    <sys_variable_value action="INSERT_OR_UPDATE">
        <document>wf_activity</document>
        <document_key>04b47b604f31030031243ce18110c782</document_key>
        <order>1310</order>
        <sys_class_name>sys_variable_value</sys_class_name>
        <sys_created_by>admin</sys_created_by>
        <sys_created_on>2017-10-11 09:10:34</sys_created_on>
        <sys_id>0ce4f7204f31030031243ce18110c7ff</sys_id>
        <sys_mod_count>0</sys_mod_count>
        <sys_updated_by>admin</sys_updated_by>
        <sys_updated_on>2017-10-11 09:10:34</sys_updated_on>
        <value>follow_up</value>
        <variable display_value="">21fd462c0a0a0b211c997276d7806c03</variable>
    </sys_variable_value>
    <sys_variable_value action="INSERT_OR_UPDATE">
        <document>wf_activity</document>
        <document_key>04b47b604f31030031243ce18110c782</document_key>
        <order>1310</order>
        <sys_class_name>sys_variable_value</sys_class_name>
        <sys_created_by>admin</sys_created_by>
        <sys_created_on>2017-10-11 09:10:34</sys_created_on>
        <sys_id>48e4f7204f31030031243ce18110c7ff</sys_id>
        <sys_mod_count>0</sys_mod_count>
        <sys_updated_by>admin</sys_updated_by>
        <sys_updated_on>2017-10-11 09:10:34</sys_updated_on>
        <value>3bf802c20a0a0b52008e2859cd8abcf2</value>
        <variable display_value="">220cd53d0a0a0b214103bdc2ec5c7ab4</variable>
    </sys_variable_value>
    <sys_variable_value action="INSERT_OR_UPDATE">
        <document>wf_activity</document>
        <document_key>04b47b604f31030031243ce18110c782</document_key>
        <order>1310</order>
        <sys_class_name>sys_variable_value</sys_class_name>
        <sys_created_by>admin</sys_created_by>
        <sys_created_on>2017-10-11 09:10:34</sys_created_on>
        <sys_id>84e4f7204f31030031243ce18110c7ff</sys_id>
        <sys_mod_count>0</sys_mod_count>
        <sys_updated_by>admin</sys_updated_by>
        <sys_updated_on>2017-10-11 09:10:34</sys_updated_on>
        <value/>
        <variable display_value="">c35dc0df0a0a0ba96248a7098d737925</variable>
    </sys_variable_value>
    <sys_variable_value action="INSERT_OR_UPDATE">
        <document>wf_activity</document>
        <document_key>04b47b604f31030031243ce18110c782</document_key>
        <order>1320</order>
        <sys_class_name>sys_variable_value</sys_class_name>
        <sys_created_by>admin</sys_created_by>
        <sys_created_on>2017-10-11 09:10:34</sys_created_on>
        <sys_id>08e43b204f31030031243ce18110c700</sys_id>
        <sys_mod_count>0</sys_mod_count>
        <sys_updated_by>admin</sys_updated_by>
        <sys_updated_on>2017-10-11 09:10:34</sys_updated_on>
        <value/>
        <variable display_value="">4cc6788c0a0a0b5200e6743c94001b16</variable>
    </sys_variable_value>
    <sys_variable_value action="INSERT_OR_UPDATE">
        <document>wf_activity</document>
        <document_key>04b47b604f31030031243ce18110c782</document_key>
        <order>1320</order>
        <sys_class_name>sys_variable_value</sys_class_name>
        <sys_created_by>admin</sys_created_by>
        <sys_created_on>2017-10-11 09:10:34</sys_created_on>
        <sys_id>44e43b204f31030031243ce18110c700</sys_id>
        <sys_mod_count>0</sys_mod_count>
        <sys_updated_by>admin</sys_updated_by>
        <sys_updated_on>2017-10-11 09:10:34</sys_updated_on>
        <value>08fcd0830a0a0b2600079f56b1adb9ae</value>
        <variable display_value="">4cc4a4030a0a0b52007334f001376dc5</variable>
    </sys_variable_value>
    <sys_variable_value action="INSERT_OR_UPDATE">
        <document>wf_activity</document>
        <document_key>04b47b604f31030031243ce18110c782</document_key>
        <order>1350</order>
        <sys_class_name>sys_variable_value</sys_class_name>
        <sys_created_by>admin</sys_created_by>
        <sys_created_on>2017-10-11 09:10:34</sys_created_on>
        <sys_id>40e43b204f31030031243ce18110c701</sys_id>
        <sys_mod_count>0</sys_mod_count>
        <sys_updated_by>admin</sys_updated_by>
        <sys_updated_on>2017-10-11 09:10:34</sys_updated_on>
        <value/>
        <variable display_value="">4cc740fe0a0a0b520025dcf8e2ff78e7</variable>
    </sys_variable_value>
    <sys_variable_value action="INSERT_OR_UPDATE">
        <document>wf_activity</document>
        <document_key>04b47b604f31030031243ce18110c782</document_key>
        <order>1350</order>
        <sys_class_name>sys_variable_value</sys_class_name>
        <sys_created_by>admin</sys_created_by>
        <sys_created_on>2017-10-11 09:10:34</sys_created_on>
        <sys_id>4ce4f7204f31030031243ce18110c7fe</sys_id>
        <sys_mod_count>0</sys_mod_count>
        <sys_updated_by>admin</sys_updated_by>
        <sys_updated_on>2017-10-11 09:10:34</sys_updated_on>
        <value/>
        <variable display_value="">4cc836da0a0a0b520083ebc07da2f47c</variable>
    </sys_variable_value>
    <sys_variable_value action="INSERT_OR_UPDATE">
        <document>wf_activity</document>
        <document_key>04b47b604f31030031243ce18110c782</document_key>
        <order>1360</order>
        <sys_class_name>sys_variable_value</sys_class_name>
        <sys_created_by>admin</sys_created_by>
        <sys_created_on>2017-10-11 09:10:34</sys_created_on>
        <sys_id>80e43b204f31030031243ce18110c700</sys_id>
        <sys_mod_count>0</sys_mod_count>
        <sys_updated_by>admin</sys_updated_by>
        <sys_updated_on>2017-10-11 09:10:34</sys_updated_on>
        <value/>
        <variable display_value="">292b2f0e0a0a0b215aa2dd2cbc578dc5</variable>
    </sys_variable_value>
    <sys_variable_value action="INSERT_OR_UPDATE">
        <document>wf_activity</document>
        <document_key>04b47b604f31030031243ce18110c782</document_key>
        <order>1360</order>
        <sys_class_name>sys_variable_value</sys_class_name>
        <sys_created_by>admin</sys_created_by>
        <sys_created_on>2017-10-11 09:10:34</sys_created_on>
        <sys_id>c8e43b204f31030031243ce18110c700</sys_id>
        <sys_mod_count>0</sys_mod_count>
        <sys_updated_by>admin</sys_updated_by>
        <sys_updated_on>2017-10-11 09:10:34</sys_updated_on>
        <value/>
        <variable display_value="">292c91070a0a0b212543d91ffde5014c</variable>
    </sys_variable_value>
    <sys_variable_value action="INSERT_OR_UPDATE">
        <document>wf_activity</document>
        <document_key>04b47b604f31030031243ce18110c782</document_key>
        <order>1360</order>
        <sys_class_name>sys_variable_value</sys_class_name>
        <sys_created_by>admin</sys_created_by>
        <sys_created_on>2017-10-11 09:10:34</sys_created_on>
        <sys_id>cce4f7204f31030031243ce18110c7ff</sys_id>
        <sys_mod_count>0</sys_mod_count>
        <sys_updated_by>admin</sys_updated_by>
        <sys_updated_on>2017-10-11 09:10:34</sys_updated_on>
        <value/>
        <variable display_value="">292bd15e0a0a0b215a040c701033e3c5</variable>
    </sys_variable_value>
    <sys_variable_value action="INSERT_OR_UPDATE">
        <document>wf_activity</document>
        <document_key>04b47b604f31030031243ce18110c782</document_key>
        <order>3000</order>
        <sys_class_name>sys_variable_value</sys_class_name>
        <sys_created_by>admin</sys_created_by>
        <sys_created_on>2017-10-11 09:10:34</sys_created_on>
        <sys_id>c0e4f7204f31030031243ce18110c7ff</sys_id>
        <sys_mod_count>0</sys_mod_count>
        <sys_updated_by>admin</sys_updated_by>
        <sys_updated_on>2017-10-11 09:10:34</sys_updated_on>
        <value>// Set 'answer' to the number of seconds this timer should wait&#13;
answer = 0;</value>
        <variable display_value="">293493710a0a0b2115e3e5b4fce1d12a</variable>
    </sys_variable_value>
    <wf_condition action="INSERT_OR_UPDATE">
        <activity display_value="Wait for Follow-up to end">04b47b604f31030031243ce18110c782</activity>
        <condition>true</condition>
        <condition_default/>
        <condition_type>standard</condition_type>
        <else_flag>false</else_flag>
        <error>false</error>
        <event>false</event>
        <event_name/>
        <is_positive>true</is_positive>
        <name>Always</name>
        <order>0</order>
        <short_description/>
        <skip_during_generate>false</skip_during_generate>
        <sys_created_by>admin</sys_created_by>
        <sys_created_on>2017-10-11 09:10:34</sys_created_on>
        <sys_id>c4e43b204f31030031243ce18110c701</sys_id>
        <sys_mod_count>0</sys_mod_count>
        <sys_updated_by>admin</sys_updated_by>
        <sys_updated_on>2017-10-11 09:10:34</sys_updated_on>
    </wf_condition>
    <wf_transition action="INSERT_OR_UPDATE">
        <condition display_value="Always">5744b3204f31030031243ce18110c7cd</condition>
        <from display_value="Begin">d344b3204f31030031243ce18110c7cd</from>
        <sys_created_by>admin</sys_created_by>
        <sys_created_on>2017-10-11 09:09:16</sys_created_on>
        <sys_id>0d94b7604f31030031243ce18110c737</sys_id>
        <sys_mod_count>0</sys_mod_count>
        <sys_updated_by>admin</sys_updated_by>
        <sys_updated_on>2017-10-11 09:09:16</sys_updated_on>
        <to display_value="Capture the follow-up date">ff64f7604f31030031243ce18110c74f</to>
    </wf_transition>
    <wf_transition action="INSERT_OR_UPDATE">
        <condition display_value="Always">c4e43b204f31030031243ce18110c701</condition>
        <from display_value="Wait for Follow-up to end">04b47b604f31030031243ce18110c782</from>
        <sys_created_by>admin</sys_created_by>
        <sys_created_on>2017-10-11 09:12:29</sys_created_on>
        <sys_id>c0557f604f31030031243ce18110c776</sys_id>
        <sys_mod_count>0</sys_mod_count>
        <sys_updated_by>admin</sys_updated_by>
        <sys_updated_on>2017-10-11 09:12:29</sys_updated_on>
        <to display_value="End">d744b3204f31030031243ce18110c7cd</to>
    </wf_transition>
    <wf_transition action="INSERT_OR_UPDATE">
        <condition display_value="Always">6284f7204f31030031243ce18110c72d</condition>
        <from display_value="Capture the follow-up date">ff64f7604f31030031243ce18110c74f</from>
        <sys_created_by>admin</sys_created_by>
        <sys_created_on>2017-10-11 09:10:40</sys_created_on>
        <sys_id>dde43b204f31030031243ce18110c701</sys_id>
        <sys_mod_count>0</sys_mod_count>
        <sys_updated_by>admin</sys_updated_by>
        <sys_updated_on>2017-10-11 09:10:40</sys_updated_on>
        <to display_value="Wait for Follow-up to end">04b47b604f31030031243ce18110c782</to>
    </wf_transition>
    <wf_estimated_runtime_config action="INSERT_OR_UPDATE">
        <estimated_run_time/>
        <no_of_data_points>1</no_of_data_points>
        <percentage_threshold_ert>20</percentage_threshold_ert>
        <sys_created_by>admin</sys_created_by>
        <sys_created_on>2017-10-11 09:08:03</sys_created_on>
        <sys_id>5f44b3204f31030031243ce18110c7cc</sys_id>
        <sys_mod_count>0</sys_mod_count>
        <sys_updated_by>admin</sys_updated_by>
        <sys_updated_on>2017-10-11 09:08:03</sys_updated_on>
        <workflow_version display_value="Myworkflow">c2b377604f31030031243ce18110c7e5</workflow_version>
    </wf_estimated_runtime_config>
    <wf_workflow_version action="update_multiple" query="workflow=1344b3204f31030031243ce18110c7cd^sys_id!=c2b377604f31030031243ce18110c7e5">
        <published>false</published>
    </wf_workflow_version>
</record_update>
